{
	"info": {
		"_postman_id": "07d92936-671a-4e52-865c-ac4853a97b1a",
		"name": "Digitalers - Gestion",
		"schema": "https://schema.getpostman.com/json/collection/v2.1.0/collection.json",
		"_exporter_id": "30267587"
	},
	"item": [
		{
			"name": "getEstudiantes (listar estudiantes)",
			"request": {
				"method": "GET",
				"header": [],
				"url": {
					"raw": "http://127.0.0.1:8080/api/v1/estudiantes",
					"protocol": "http",
					"host": [
						"127",
						"0",
						"0",
						"1"
					],
					"port": "8080",
					"path": [
						"api",
						"v1",
						"estudiantes"
					]
				}
			},
			"response": []
		},
		{
			"name": "getEstudianteById (listar estudiantes por id)",
			"request": {
				"method": "GET",
				"header": [],
				"url": {
					"raw": "http://127.0.0.1:8080/api/v1/estudiantes/1",
					"protocol": "http",
					"host": [
						"127",
						"0",
						"0",
						"1"
					],
					"port": "8080",
					"path": [
						"api",
						"v1",
						"estudiantes",
						"1"
					]
				}
			},
			"response": []
		},
		{
			"name": "postEstudiante (añadir un estudiante)",
			"request": {
				"method": "POST",
				"header": [],
				"body": {
					"mode": "raw",
					"raw": "{\r\n    \"nombre\": \"Tessa\",\r\n    \"apellido\": \"Castellarin\",\r\n    \"fechaDeNacimiento\": \"2016-08-02\"\r\n}",
					"options": {
						"raw": {
							"language": "json"
						}
					}
				},
				"url": {
					"raw": "http://127.0.0.1:8080/api/v1/estudiantes/add",
					"protocol": "http",
					"host": [
						"127",
						"0",
						"0",
						"1"
					],
					"port": "8080",
					"path": [
						"api",
						"v1",
						"estudiantes",
						"add"
					]
				}
			},
			"response": []
		},
		{
			"name": "putEstudiante (editar estudiante)",
			"request": {
				"method": "PUT",
				"header": [],
				"body": {
					"mode": "raw",
					"raw": "{\r\n    \"nombre\": \"Tessa\",\r\n    \"apellido\": \"Castellarin\",\r\n    \"fechaDeNacimiento\": \"2016-09-02\"\r\n}",
					"options": {
						"raw": {
							"language": "json"
						}
					}
				},
				"url": {
					"raw": "http://127.0.0.1:8080/api/v1/estudiantes/edit/1",
					"protocol": "http",
					"host": [
						"127",
						"0",
						"0",
						"1"
					],
					"port": "8080",
					"path": [
						"api",
						"v1",
						"estudiantes",
						"edit",
						"1"
					]
				}
			},
			"response": []
		},
		{
			"name": "deleteEstudiante (eliminar estudiante)",
			"request": {
				"method": "DELETE",
				"header": [],
				"url": {
					"raw": "http://127.0.0.1:8080/api/v1/estudiantes/2",
					"protocol": "http",
					"host": [
						"127",
						"0",
						"0",
						"1"
					],
					"port": "8080",
					"path": [
						"api",
						"v1",
						"estudiantes",
						"2"
					]
				}
			},
			"response": []
		}
	]
}